odoo8_addon_hr_employee_reference-8.0.1.0.0.99.dev4-py2.7-nspkg.pth
odoo8_addon_hr_employee_reference-8.0.1.0.0.99.dev4.dist-info/DESCRIPTION.rst
odoo8_addon_hr_employee_reference-8.0.1.0.0.99.dev4.dist-info/METADATA
odoo8_addon_hr_employee_reference-8.0.1.0.0.99.dev4.dist-info/RECORD
odoo8_addon_hr_employee_reference-8.0.1.0.0.99.dev4.dist-info/WHEEL
odoo8_addon_hr_employee_reference-8.0.1.0.0.99.dev4.dist-info/metadata.json
odoo8_addon_hr_employee_reference-8.0.1.0.0.99.dev4.dist-info/namespace_packages.txt
odoo8_addon_hr_employee_reference-8.0.1.0.0.99.dev4.dist-info/top_level.txt
odoo_addons/hr_employee_reference/README.rst
odoo_addons/hr_employee_reference/__init__.py
odoo_addons/hr_employee_reference/__openerp__.py
odoo_addons/hr_employee_reference/i18n/ar.po
odoo_addons/hr_employee_reference/i18n/de.po
odoo_addons/hr_employee_reference/i18n/es.po
odoo_addons/hr_employee_reference/i18n/fi.po
odoo_addons/hr_employee_reference/i18n/fr.po
odoo_addons/hr_employee_reference/i18n/hr_employee_reference.pot
odoo_addons/hr_employee_reference/i18n/it.po
odoo_addons/hr_employee_reference/i18n/nl.po
odoo_addons/hr_employee_reference/i18n/nl_NL.po
odoo_addons/hr_employee_reference/i18n/pt_BR.po
odoo_addons/hr_employee_reference/i18n/ro.po
odoo_addons/hr_employee_reference/i18n/sl.po
odoo_addons/hr_employee_reference/models/__init__.py
odoo_addons/hr_employee_reference/models/hr_employee.py
odoo_addons/hr_employee_reference/static/description/icon.png
odoo_addons/hr_employee_reference/views/hr_employee_views.xml
